textlocal/api.py
textlocal/contacts.py
textlocal/exceptions.py
textlocal/messages.py
textlocal/models.py
textlocal/__init__.py
textlocal/test/test_api.py
textlocal/test/test_contacts.py
textlocal/test/test_messages.py
textlocal/test/test_models.py
textlocal/test/__init__.py
textlocal-0.1.0.dist-info/DESCRIPTION.rst
textlocal-0.1.0.dist-info/METADATA
textlocal-0.1.0.dist-info/metadata.json
textlocal-0.1.0.dist-info/RECORD
textlocal-0.1.0.dist-info/top_level.txt
textlocal-0.1.0.dist-info/WHEEL
