Metadata-Version: 2.0
Name: textlocal
Version: 0.1.0
Summary: UNKNOWN
Home-page: UNKNOWN
Author: James Fenwick
Author-email: j.fenwick@me.com
License: UNKNOWN
Platform: UNKNOWN
Requires-Dist: requests (==2.9.1)
Requires-Dist: phonenumbers (==7.2.4)
